README.md
setup.py
bert_augment/__init__.py
bert_augment/bert_augment.py
bert_augment/test_bert_augment.py
bert_augment.egg-info/PKG-INFO
bert_augment.egg-info/SOURCES.txt
bert_augment.egg-info/dependency_links.txt
bert_augment.egg-info/entry_points.txt
bert_augment.egg-info/requires.txt
bert_augment.egg-info/top_level.txt