Metadata-Version: 2.1
Name: bert-augment
Version: 0.0
Summary: BERT based text augmentation
Home-page: https://github.com/gkutiel/BERTAugment
Author: Gilad Kutiel
Author-email: gilad.kutiel@gmail.com
License: UNKNOWN
Platform: UNKNOWN
Requires-Python: >=3.7
